hueymail/__init__.py
hueymail/_version.py
hueymail/backends.py
hueymail/tasks.py
django_huey_email_backend-0.1.1.dist-info/LICENSE
django_huey_email_backend-0.1.1.dist-info/METADATA
django_huey_email_backend-0.1.1.dist-info/WHEEL
django_huey_email_backend-0.1.1.dist-info/top_level.txt
django_huey_email_backend-0.1.1.dist-info/RECORD
