Metadata-Version: 2.1
Name: django-huey-email-backend
Version: 0.1.1
Summary: Django email backend using Huey
Home-page: https://github.com/chris-mcdo/django-huey-email-backend
Author: Christopher McDonald
Author-email: cmcdonal33@gmail.com
License: MIT
Project-URL: Source, https://github.com/chris-mcdo/django-huey-email-backend
Project-URL: Tracker, https://github.com/chris-mcdo/django-huey-email-backend/issues
Keywords: django,huey,email,backend
Platform: win32
Platform: linux
Platform: osx
Classifier: Development Status :: 4 - Beta
Classifier: Intended Audience :: Developers
Classifier: License :: OSI Approved :: MIT License
Classifier: Operating System :: MacOS :: MacOS X
Classifier: Operating System :: Microsoft :: Windows
Classifier: Operating System :: POSIX
Classifier: Programming Language :: Python :: 3
Classifier: Programming Language :: Python :: 3 :: Only
Classifier: Programming Language :: Python :: 3.8
Classifier: Programming Language :: Python :: 3.9
Classifier: Programming Language :: Python :: 3.10
Classifier: Topic :: Internet
Classifier: Topic :: Internet :: WWW/HTTP
Classifier: Environment :: Web Environment
Classifier: Framework :: Django
Classifier: Framework :: Django :: 4
Classifier: Framework :: Django :: 4.0
Requires-Python: >=3.4
License-File: LICENSE
